MANIFEST.in
README.md
setup.py
ASSETOOL/get_resources.py
ASSETOOL/prehandle.py
ASSETOOL/resource.py
estring/__init__.py
estring/consts.py
estring/estring.py
estring/h5entity.py
estring.egg-info/PKG-INFO
estring.egg-info/SOURCES.txt
estring.egg-info/dependency_links.txt
estring.egg-info/entry_points.txt
estring.egg-info/top_level.txt
estring/BINS/__init__.py
estring/BINS/camel2dash.py
estring/BINS/camel2lod.py
estring/BINS/capinit.py
estring/BINS/dash2camel.py
estring/BINS/dash2lod.py
estring/BINS/emoji.py
estring/BINS/h5entity.py
estring/BINS/lod2camel.py
estring/BINS/lod2dash.py
estring/Images/append.0.png
estring/Images/bytnums2chnums.0.png
estring/Images/bytnums2hex.0.png
estring/Images/bytnums2str.0.png
estring/Images/bytnums2strm.0.png
estring/Images/bytnums2us.0.png
estring/Images/byts2chnum.0.png
estring/Images/bytstrm2chnums.0.png
estring/Images/bytstrm2hex.0.png
estring/Images/bytstrm2us.0.png
estring/Images/bytstrm2us.1.png
estring/Images/charAt.0.png
estring/Images/charAt.1.png
estring/Images/charCodeAt.0.png
estring/Images/charCodeAt.1.png
estring/Images/chnums2bytnums.0.png
estring/Images/chnums2bytstrm.0.png
estring/Images/chnums2hex.0.png
estring/Images/chnums2str.0.png
estring/Images/chnums2us.0.png
estring/Images/codePointAt.0.png
estring/Images/codePointAt.1.png
estring/Images/decode_bytstrm.0.png
estring/Images/decode_chbyts.0.png
estring/Images/display_width.0.png
estring/Images/divide.0.png
estring/Images/endsWith.0.png
estring/Images/fromCharCode.0.png
estring/Images/get_bominfo.0.png
estring/Images/get_bomtype.0.png
estring/Images/get_bomtype.1.png
estring/Images/head2tail.0.png
estring/Images/hex2bytnums.0.png
estring/Images/hex2bytstrm.0.png
estring/Images/hex2chnums.0.png
estring/Images/hex2str.0.png
estring/Images/hex2us.0.png
estring/Images/indexesAll.0.png
estring/Images/jscharpoints2pychpoints.0.png
estring/Images/length.0.png
estring/Images/length.1.png
estring/Images/lstrip.0.png
estring/Images/pack_chnum.0.png
estring/Images/pack_chstr.0.png
estring/Images/packstr.0.png
estring/Images/padEnd.0.png
estring/Images/padStart.0.png
estring/Images/prepend.0.png
